pdf_to_xls/__init__.py
pdf_to_xls/config.py
pdf_to_xls/converter.py
pdf_to_xls/data_cleaning.py
pdf_to_xls/excel_writer.py
pdf_to_xls/image_processing.py
pdf_to_xls/pdf_detection.py
pdf_to_xls/quality_check.py
pdf_to_xls/table_extraction.py
pdf_to_xls_vision-1.0.0.dist-info/licenses/LICENSE
pdf_to_xls_vision-1.0.0.dist-info/METADATA
pdf_to_xls_vision-1.0.0.dist-info/WHEEL
pdf_to_xls_vision-1.0.0.dist-info/entry_points.txt
pdf_to_xls_vision-1.0.0.dist-info/top_level.txt
pdf_to_xls_vision-1.0.0.dist-info/RECORD
