Metadata-Version: 2.4
Name: pdf-to-xls-vision
Version: 1.0.0
Summary: Convert PDF tables to Excel using Claude Vision API with automatic rotation detection
Home-page: https://github.com/yourusername/pdf-to-xls-vision
Author: Your Name
Author-email: Your Name <your.email@example.com>
License: MIT
Project-URL: Homepage, https://github.com/yourusername/pdf-to-xls-vision
Project-URL: Documentation, https://github.com/yourusername/pdf-to-xls-vision#readme
Project-URL: Repository, https://github.com/yourusername/pdf-to-xls-vision
Project-URL: Bug Tracker, https://github.com/yourusername/pdf-to-xls-vision/issues
Keywords: pdf,excel,conversion,vision-api,claude,anthropic,ocr,table-extraction
Classifier: Development Status :: 4 - Beta
Classifier: Intended Audience :: Developers
Classifier: Topic :: Software Development :: Libraries :: Python Modules
Classifier: Topic :: Office/Business
Classifier: License :: OSI Approved :: MIT License
Classifier: Programming Language :: Python :: 3
Classifier: Programming Language :: Python :: 3.7
Classifier: Programming Language :: Python :: 3.8
Classifier: Programming Language :: Python :: 3.9
Classifier: Programming Language :: Python :: 3.10
Classifier: Programming Language :: Python :: 3.11
Classifier: Programming Language :: Python :: 3.12
Requires-Python: >=3.7
License-File: LICENSE
Requires-Dist: pdfplumber>=0.10.0
Requires-Dist: pandas>=2.0.0
Requires-Dist: openpyxl>=3.1.0
Requires-Dist: anthropic>=0.69.0
Requires-Dist: python-dotenv>=1.0.0
Requires-Dist: pdf2image>=1.17.0
Requires-Dist: pillow>=9.1.0
Requires-Dist: pytesseract>=0.3.10
Requires-Dist: PyMuPDF>=1.23.0
Dynamic: author
Dynamic: home-page
Dynamic: license-file
Dynamic: requires-python
